depth/__init__.py
depth/model/DepthEucl.py
depth/model/__init__.py
depth/model/docHelp.py
depth/model/multivariate/ACA_wrapper.py
depth/model/multivariate/Aprojection.py
depth/model/multivariate/BetaSkeleton.py
depth/model/multivariate/CUDA_approximation.py
depth/model/multivariate/Cexpchull.py
depth/model/multivariate/Cexpchullstar.py
depth/model/multivariate/Depth_approximation.py
depth/model/multivariate/Geometrical.py
depth/model/multivariate/Halfspace.py
depth/model/multivariate/L2.py
depth/model/multivariate/MCD.py
depth/model/multivariate/Mahalanobis.py
depth/model/multivariate/Potential.py
depth/model/multivariate/Projection.py
depth/model/multivariate/Qhpeeling.py
depth/model/multivariate/Simplicial.py
depth/model/multivariate/SimplicialVolume.py
depth/model/multivariate/Spatial.py
depth/model/multivariate/Zonoid.py
depth/model/multivariate/__init__.py
depth/model/multivariate/import_CDLL.py
depth/model/multivariate/plot.py
depth/plotDepth/__init__.py
depth/plotDepth/depth_mesh.py
depth/plotDepth/depth_plot2d.py
depth/src/ACA_wrapper.dll
depth/src/ddalpha.dll
depth/src/depth_wrapper.dll
depth/src/libatomic-1.dll
depth/src/libgcc_s_dw2-1.dll
depth/src/libgcc_s_seh-1.dll
depth/src/libgfortran-3.dll
depth/src/libgmp-10.dll
depth/src/libgmpxx-4.dll
depth/src/libgomp-1.dll
depth/src/libgomp-plugin-host_nonshm-1.dll
depth/src/libquadmath-0.dll
depth/src/libssp-0.dll
depth/src/libstdc++-6.dll
depth/src/libvtv-0.dll
depth/src/libvtv_stubs-0.dll
depth/src/libwinpthread-1.dll
data_depth-1.1.2.5.dist-info/METADATA
data_depth-1.1.2.5.dist-info/WHEEL
data_depth-1.1.2.5.dist-info/top_level.txt
data_depth-1.1.2.5.dist-info/RECORD
